gpt_image/__init__.py
gpt_image/disk.py
gpt_image/geometry.py
gpt_image/partition.py
gpt_image/py.typed
gpt_image/table.py
gpt_image-0.9.1.dist-info/licenses/LICENSE
gpt_image-0.9.1.dist-info/METADATA
gpt_image-0.9.1.dist-info/WHEEL
gpt_image-0.9.1.dist-info/top_level.txt
gpt_image-0.9.1.dist-info/RECORD
