Metadata-Version: 2.4
Name: gpt-image
Version: 0.9.1
Summary: Build GPT Disk Images on Local Drives
Home-page: https://github.com/swysocki/gpt-image
Author: Scott Wysocki
Author-email: swysocki@gmail.com
License: MIT
Requires-Python: >=3.8
License-File: LICENSE
Dynamic: license-file
